calculator_102.py
calculator_102-0.1.7.dist-info/LICENSE
calculator_102-0.1.7.dist-info/WHEEL
calculator_102-0.1.7.dist-info/METADATA
calculator_102-0.1.7.dist-info/RECORD
