Metadata-Version: 2.1
Name: calculator_102
Version: 0.1.7
Summary: Simple calculator package
Author-email: Jolanta <jolanta3210@gmail.com>
Classifier: License :: OSI Approved :: MIT License
